Metadata-Version: 1.0
Name: ja-ginza-dict
Version: 3.1.0
Summary: SudachiDict for ja_ginza (SudachiDict is originally developed by Works Applications Tokushima Laboratory of AI and NLP)
Home-page: https://github.com/megagonlabs/ginza
Author: Megagon Labs, Tokyo.
Author-email: ginza@megagon.ai
License: MIT
Platform: UNKNOWN
